jn_space_corrector/__init__.py
jn_space_corrector/jn_spacing.py
jn_space_corrector/src/__init__.py
jn_space_corrector/src/models.py
jn_space_corrector/src/preprocessing.py
jn_space_corrector-0.0.6.dist-info/METADATA
jn_space_corrector-0.0.6.dist-info/WHEEL
jn_space_corrector-0.0.6.dist-info/top_level.txt
jn_space_corrector-0.0.6.dist-info/zip-safe
jn_space_corrector-0.0.6.dist-info/RECORD
